[{"__type__":"cc.SpriteFrame","content":{"name":"roll04","texture":"51634a31-9144-41e9-83cb-706c722f89e0","rect":[444,2,120,127],"offset":[0,1],"originalSize":[180,145]}},{"__type__":"cc.SpriteFrame","content":{"name":"roll06","texture":"51634a31-9144-41e9-83cb-706c722f89e0","rect":[158,2,142,127],"offset":[0,1],"originalSize":[180,145]}},{"__type__":"cc.SpriteFrame","content":{"name":"roll01","texture":"51634a31-9144-41e9-83cb-706c722f89e0","rect":[832,2,114,133],"offset":[0,1],"originalSize":[180,145],"rotated":1}},{"__type__":"cc.SpriteFrame","content":{"name":"roll07","texture":"51634a31-9144-41e9-83cb-706c722f89e0","rect":[302,2,140,127],"offset":[0,1],"originalSize":[180,145]}},{"__type__":"cc.SpriteFrame","content":{"name":"roll05","texture":"51634a31-9144-41e9-83cb-706c722f89e0","rect":[2,2,154,129],"offset":[-1,1],"originalSize":[180,145]}},[{"__type__":"cc.Prefab","_name":"pb_LineGameFruit","data":{"__id__":1},"asyncLoadAssets":false},{"__type__":"cc.Node","_name":"pb_Fruit","_children":[{"__id__":2},{"__id__":3}],"_components":[{"__type__":"cc.Sprite","node":{"__id__":1},"_sizeMode":0,"_isTrimmedMode":false},{"__type__":"820c9nOWnlLcYrrd8lXtwCJ","node":{"__id__":1},"sp_FruitSpriteFrame":[{"__uuid__":"38c83046-b2cc-43db-b9ba-7a6974b53c57"},{"__uuid__":"e4974148-67fc-4c2c-822e-dacf46b6ebf6"},{"__uuid__":"e575d866-726e-4461-99d5-29751ea5fcb1"},{"__uuid__":"0b19ee5f-60b7-4a96-8d28-fdec11323bf3"},{"__uuid__":"6a57bc24-94fc-417b-b047-168ac47d48fb"},{"__uuid__":"11f50b56-7f00-4c03-9fae-a0e48efa6d02"},{"__uuid__":"584517d4-98db-4765-8290-b59a6c9d6c9f"}]}],"_prefab":{"__type__":"cc.PrefabInfo","root":{"__id__":1},"fileId":"9f72fYMT4FLA4KY15cu0QW4"},"_contentSize":{"__type__":"cc.Size","width":180,"height":145}},{"__type__":"cc.Node","_name":"sp_Fruit","_parent":{"__id__":1},"_components":[{"__type__":"cc.Sprite","node":{"__id__":2},"_spriteFrame":{"__uuid__":"584517d4-98db-4765-8290-b59a6c9d6c9f"},"_sizeMode":0,"_isTrimmedMode":false}],"_prefab":{"__type__":"cc.PrefabInfo","root":{"__id__":1},"fileId":"0e18ahZAftPNpH46m5wVRfe"},"_contentSize":{"__type__":"cc.Size","width":180,"height":145}},{"__type__":"cc.Node","_name":"db_Animation","_parent":{"__id__":1},"_components":[{"__type__":"dragonBones.ArmatureDisplay","node":{"__id__":3},"_armatureName":"roll","_N$dragonAsset":{"__uuid__":"8583e1b6-4d5a-4264-9323-e8f747df3524"},"_N$dragonAtlasAsset":{"__uuid__":"d4aab086-5799-4526-ae8c-e7c5d3da9242"}}],"_prefab":{"__type__":"cc.PrefabInfo","root":{"__id__":1},"fileId":"1c697akuoZDXpFQOXI92IYa"}}],{"__type__":"cc.SpriteFrame","content":{"name":"roll02","texture":"51634a31-9144-41e9-83cb-706c722f89e0","rect":[699,2,120,131],"offset":[0,0],"originalSize":[180,145],"rotated":1}},{"__type__":"cc.SpriteFrame","content":{"name":"roll03","texture":"51634a31-9144-41e9-83cb-706c722f89e0","rect":[566,2,120,131],"offset":[0,1],"originalSize":[180,145],"rotated":1}}]